{
  "text": "בֵּאדַ֡יִן מִֽתְכַּנְּשִׁ֡ין אֲחַשְׁדַּרְפְּנַיָּ֡א סִגְנַיָּ֣א וּֽפַחֲוָתָ֡א אֲדַרְגָּזְרַיָּ֣א גְדָבְרַיָּא֩ דְּתָ֨בְרַיָּ֜א תִּפְתָּיֵ֗א וְכֹל֙ שִׁלְטֹנֵ֣י מְדִֽינָתָ֔א לַחֲנֻכַּ֣ת צַלְמָ֔א דִּ֥י הֲקֵ֖ים נְבוּכַדְנֶצַּ֣ר מַלְכָּ֑א וקאמין לָקֳבֵ֣ל צַלְמָ֔א דִּ֥י הֲקֵ֖ים נְבוּכַדְנֶצַּֽר וְקָֽיְמִין֙",
  "words": [
    {
      "position": 1,
      "text": "בֵּאדַ֡יִן",
      "lemma": "b/116",
      "morph": "AR/D",
      "strongs": [
        "H116"
      ],
      "metadata": {},
      "source": {
        "lemma": "b/116",
        "morph": "AR/D"
      }
    },
    {
      "position": 2,
      "text": "מִֽתְכַּנְּשִׁ֡ין",
      "lemma": "3673",
      "morph": "AVMrmpa",
      "strongs": [
        "H3673"
      ],
      "metadata": {},
      "source": {
        "lemma": "3673",
        "morph": "AVMrmpa"
      }
    },
    {
      "position": 3,
      "text": "אֲחַשְׁדַּרְפְּנַיָּ֡א",
      "lemma": "324",
      "morph": "ANcmpd/Td",
      "strongs": [
        "H324"
      ],
      "metadata": {},
      "source": {
        "lemma": "324",
        "morph": "ANcmpd/Td"
      }
    },
    {
      "position": 4,
      "text": "סִגְנַיָּ֣א",
      "lemma": "5460",
      "morph": "ANcmpd/Td",
      "strongs": [
        "H5460"
      ],
      "metadata": {},
      "source": {
        "lemma": "5460",
        "morph": "ANcmpd/Td"
      }
    },
    {
      "position": 5,
      "text": "וּֽפַחֲוָתָ֡א",
      "lemma": "c/6347",
      "morph": "AC/Ncmpd/Td",
      "strongs": [
        "H6347"
      ],
      "metadata": {},
      "source": {
        "lemma": "c/6347",
        "morph": "AC/Ncmpd/Td"
      }
    },
    {
      "position": 6,
      "text": "אֲדַרְגָּזְרַיָּ֣א",
      "lemma": "148",
      "morph": "ANcmpd/Td",
      "strongs": [
        "H148"
      ],
      "metadata": {},
      "source": {
        "lemma": "148",
        "morph": "ANcmpd/Td"
      }
    },
    {
      "position": 7,
      "text": "גְדָבְרַיָּא֩",
      "lemma": "1411",
      "morph": "ANcmpd/Td",
      "strongs": [
        "H1411"
      ],
      "metadata": {},
      "source": {
        "lemma": "1411",
        "morph": "ANcmpd/Td"
      }
    },
    {
      "position": 8,
      "text": "דְּתָ֨בְרַיָּ֜א",
      "lemma": "1884",
      "morph": "ANcmpd/Td",
      "strongs": [
        "H1884"
      ],
      "metadata": {},
      "source": {
        "lemma": "1884",
        "morph": "ANcmpd/Td"
      }
    },
    {
      "position": 9,
      "text": "תִּפְתָּיֵ֗א",
      "lemma": "8614",
      "morph": "ANcmpd/Td",
      "strongs": [
        "H8614"
      ],
      "metadata": {},
      "source": {
        "lemma": "8614",
        "morph": "ANcmpd/Td"
      }
    },
    {
      "position": 10,
      "text": "וְכֹל֙",
      "lemma": "c/3606",
      "morph": "AC/Ncmsc",
      "strongs": [
        "H3606"
      ],
      "metadata": {},
      "source": {
        "lemma": "c/3606",
        "morph": "AC/Ncmsc"
      }
    },
    {
      "position": 11,
      "text": "שִׁלְטֹנֵ֣י",
      "lemma": "7984",
      "morph": "ANcmpc",
      "strongs": [
        "H7984"
      ],
      "metadata": {},
      "source": {
        "lemma": "7984",
        "morph": "ANcmpc"
      }
    },
    {
      "position": 12,
      "text": "מְדִֽינָתָ֔א",
      "lemma": "4083",
      "morph": "ANcfsd/Td",
      "strongs": [
        "H4083"
      ],
      "metadata": {},
      "source": {
        "lemma": "4083",
        "morph": "ANcfsd/Td"
      }
    },
    {
      "position": 13,
      "text": "לַחֲנֻכַּ֣ת",
      "lemma": "l/2597",
      "morph": "AC/Ncfsc",
      "strongs": [
        "H2597"
      ],
      "metadata": {},
      "source": {
        "lemma": "l/2597",
        "morph": "AC/Ncfsc"
      }
    },
    {
      "position": 14,
      "text": "צַלְמָ֔א",
      "lemma": "6755",
      "morph": "ANcmsd/Td",
      "strongs": [
        "H6755"
      ],
      "metadata": {},
      "source": {
        "lemma": "6755",
        "morph": "ANcmsd/Td"
      }
    },
    {
      "position": 15,
      "text": "דִּ֥י",
      "lemma": "1768",
      "morph": "ATr",
      "strongs": [
        "H1768"
      ],
      "metadata": {},
      "source": {
        "lemma": "1768",
        "morph": "ATr"
      }
    },
    {
      "position": 16,
      "text": "הֲקֵ֖ים",
      "lemma": "6966",
      "morph": "AVhp3ms",
      "strongs": [
        "H6966"
      ],
      "metadata": {},
      "source": {
        "lemma": "6966",
        "morph": "AVhp3ms"
      }
    },
    {
      "position": 17,
      "text": "נְבוּכַדְנֶצַּ֣ר",
      "lemma": "5020",
      "morph": "ANp",
      "strongs": [
        "H5020"
      ],
      "metadata": {},
      "source": {
        "lemma": "5020",
        "morph": "ANp"
      }
    },
    {
      "position": 18,
      "text": "מַלְכָּ֑א",
      "lemma": "4430",
      "morph": "ANcmsd/Td",
      "strongs": [
        "H4430"
      ],
      "metadata": {},
      "source": {
        "lemma": "4430",
        "morph": "ANcmsd/Td"
      }
    },
    {
      "position": 19,
      "text": "וקאמין",
      "lemma": "c/6966",
      "morph": "AC/Vqrmpa",
      "strongs": [
        "H6966"
      ],
      "variant": "ketiv",
      "metadata": {},
      "source": {
        "lemma": "c/6966",
        "morph": "AC/Vqrmpa",
        "type": "x-ketiv"
      }
    },
    {
      "position": 20,
      "text": "לָקֳבֵ֣ל",
      "lemma": "l/6903",
      "morph": "AR/R",
      "strongs": [
        "H6903"
      ],
      "metadata": {},
      "source": {
        "lemma": "l/6903",
        "morph": "AR/R"
      }
    },
    {
      "position": 21,
      "text": "צַלְמָ֔א",
      "lemma": "6755",
      "morph": "ANcmsd/Td",
      "strongs": [
        "H6755"
      ],
      "metadata": {},
      "source": {
        "lemma": "6755",
        "morph": "ANcmsd/Td"
      }
    },
    {
      "position": 22,
      "text": "דִּ֥י",
      "lemma": "1768",
      "morph": "ATr",
      "strongs": [
        "H1768"
      ],
      "metadata": {},
      "source": {
        "lemma": "1768",
        "morph": "ATr"
      }
    },
    {
      "position": 23,
      "text": "הֲקֵ֖ים",
      "lemma": "6966",
      "morph": "AVhp3ms",
      "strongs": [
        "H6966"
      ],
      "metadata": {},
      "source": {
        "lemma": "6966",
        "morph": "AVhp3ms"
      }
    },
    {
      "position": 24,
      "text": "נְבוּכַדְנֶצַּֽר",
      "lemma": "5020",
      "morph": "ANp",
      "strongs": [
        "H5020"
      ],
      "metadata": {},
      "source": {
        "lemma": "5020",
        "morph": "ANp"
      }
    },
    {
      "position": 25,
      "text": "וְקָֽיְמִין֙",
      "lemma": "c/6966",
      "morph": "AC/Vqrmpa",
      "strongs": [
        "H6966"
      ],
      "variant": "qere",
      "metadata": {},
      "source": {
        "lemma": "c/6966",
        "morph": "AC/Vqrmpa"
      }
    }
  ]
}