{
  "text": "וְעַתָּה אֱלֹהֵינוּ מוֹדִים אֲנַחְנוּ לָךְ וּמְהַלְלִים לְשֵׁם תִּפְאַרְתֶּךָ",
  "words": [
    {
      "position": 1,
      "text": "וְעַתָּה",
      "lemma": "c/6258",
      "morph": "HC/D",
      "strongs": [
        "H6258"
      ],
      "metadata": {},
      "gematria": {
        "standard": 481,
        "ordinal": 49,
        "reduced": 22
      }
    },
    {
      "position": 2,
      "text": "אֱלֹהֵינוּ",
      "lemma": "430",
      "morph": "HNcmpc/Sp1cp",
      "strongs": [
        "H430"
      ],
      "metadata": {},
      "gematria": {
        "standard": 102,
        "ordinal": 48,
        "reduced": 21
      }
    },
    {
      "position": 3,
      "text": "מוֹדִים",
      "lemma": "3034",
      "morph": "HVhrmpa",
      "strongs": [
        "H3034"
      ],
      "metadata": {},
      "gematria": {
        "standard": 100,
        "ordinal": 57,
        "reduced": 19
      }
    },
    {
      "position": 4,
      "text": "אֲנַחְנוּ",
      "lemma": "587",
      "morph": "HPp1cp",
      "strongs": [
        "H587"
      ],
      "metadata": {},
      "gematria": {
        "standard": 115,
        "ordinal": 43,
        "reduced": 25
      }
    },
    {
      "position": 5,
      "text": "לָךְ",
      "lemma": "l",
      "morph": "HR/Sp2fs",
      "metadata": {},
      "gematria": {
        "standard": 50,
        "ordinal": 35,
        "reduced": 5
      }
    },
    {
      "position": 6,
      "text": "וּמְהַלְלִים",
      "lemma": "c/1984 b",
      "morph": "HC/Vprmpa",
      "strongs": [
        "H1984"
      ],
      "metadata": {},
      "gematria": {
        "standard": 161,
        "ordinal": 82,
        "reduced": 26
      }
    },
    {
      "position": 7,
      "text": "לְשֵׁם",
      "lemma": "l/8034",
      "morph": "HR/Ncmsc",
      "strongs": [
        "H8034"
      ],
      "metadata": {},
      "gematria": {
        "standard": 370,
        "ordinal": 57,
        "reduced": 10
      }
    },
    {
      "position": 8,
      "text": "תִּפְאַרְתֶּךָ",
      "lemma": "8597",
      "morph": "HNcfsc/Sp2ms",
      "strongs": [
        "H8597"
      ],
      "metadata": {},
      "gematria": {
        "standard": 1101,
        "ordinal": 105,
        "reduced": 21
      }
    }
  ],
  "gematria": {
    "standard": 2480,
    "ordinal": 476,
    "reduced": 149
  }
}