{
  "text": "וַיֵּצֵא נֹחַ וּבָנָיו וְאִשְׁתּוֹ וּנְשֵׁי בָנָיו אִתּוֹ",
  "words": [
    {
      "position": 1,
      "text": "וַיֵּצֵא",
      "lemma": "c/3318",
      "morph": "HC/Vqw3ms",
      "strongs": [
        "H3318"
      ],
      "metadata": {},
      "gematria": {
        "standard": 107,
        "ordinal": 35,
        "reduced": 17
      }
    },
    {
      "position": 2,
      "text": "נֹחַ",
      "lemma": "5146",
      "morph": "HNp",
      "strongs": [
        "H5146"
      ],
      "metadata": {},
      "gematria": {
        "standard": 58,
        "ordinal": 22,
        "reduced": 13
      }
    },
    {
      "position": 3,
      "text": "וּבָנָיו",
      "lemma": "c/1121 a",
      "morph": "HC/Ncmpc/Sp3ms",
      "strongs": [
        "H1121"
      ],
      "metadata": {},
      "gematria": {
        "standard": 74,
        "ordinal": 38,
        "reduced": 20
      }
    },
    {
      "position": 4,
      "text": "וְאִשְׁתּוֹ",
      "lemma": "c/802",
      "morph": "HC/Ncfsc/Sp3ms",
      "strongs": [
        "H802"
      ],
      "metadata": {},
      "gematria": {
        "standard": 713,
        "ordinal": 56,
        "reduced": 20
      }
    },
    {
      "position": 5,
      "text": "וּנְשֵׁי",
      "lemma": "c/802",
      "morph": "HC/Ncfpc",
      "strongs": [
        "H802"
      ],
      "metadata": {},
      "gematria": {
        "standard": 366,
        "ordinal": 51,
        "reduced": 15
      }
    },
    {
      "position": 6,
      "text": "בָנָיו",
      "lemma": "1121 a",
      "morph": "HNcmpc/Sp3ms",
      "strongs": [
        "H1121"
      ],
      "metadata": {},
      "gematria": {
        "standard": 68,
        "ordinal": 32,
        "reduced": 14
      }
    },
    {
      "position": 7,
      "text": "אִתּוֹ",
      "lemma": "854",
      "morph": "HR/Sp3ms",
      "strongs": [
        "H854"
      ],
      "metadata": {},
      "gematria": {
        "standard": 407,
        "ordinal": 29,
        "reduced": 11
      }
    }
  ],
  "gematria": {
    "standard": 1793,
    "ordinal": 263,
    "reduced": 110
  }
}