{
  "text": "וַתֵּ֥לֶד עָדָ֖ה אֶת יָבָ֑ל ה֣וּא הָיָ֔ה אֲבִ֕י יֹשֵׁ֥ב אֹ֖הֶל וּמִקְנֶֽה",
  "words": [
    {
      "position": 1,
      "text": "וַתֵּ֥לֶד",
      "lemma": "c/3205",
      "morph": "HC/Vqw3fs",
      "strongs": [
        "H3205"
      ],
      "metadata": {},
      "source": {
        "lemma": "c/3205",
        "morph": "HC/Vqw3fs"
      }
    },
    {
      "position": 2,
      "text": "עָדָ֖ה",
      "lemma": "5711",
      "morph": "HNp",
      "strongs": [
        "H5711"
      ],
      "metadata": {},
      "source": {
        "lemma": "5711",
        "morph": "HNp"
      }
    },
    {
      "position": 3,
      "text": "אֶת",
      "lemma": "853",
      "morph": "HTo",
      "strongs": [
        "H853"
      ],
      "metadata": {},
      "source": {
        "lemma": "853",
        "morph": "HTo"
      }
    },
    {
      "position": 4,
      "text": "יָבָ֑ל",
      "lemma": "2989",
      "morph": "HNp",
      "strongs": [
        "H2989"
      ],
      "metadata": {},
      "source": {
        "lemma": "2989",
        "morph": "HNp"
      }
    },
    {
      "position": 5,
      "text": "ה֣וּא",
      "lemma": "1931",
      "morph": "HPp3ms",
      "strongs": [
        "H1931"
      ],
      "metadata": {},
      "source": {
        "lemma": "1931",
        "morph": "HPp3ms"
      }
    },
    {
      "position": 6,
      "text": "הָיָ֔ה",
      "lemma": "1961",
      "morph": "HVqp3ms",
      "strongs": [
        "H1961"
      ],
      "metadata": {},
      "source": {
        "lemma": "1961",
        "morph": "HVqp3ms"
      }
    },
    {
      "position": 7,
      "text": "אֲבִ֕י",
      "lemma": "1",
      "morph": "HNcmsc",
      "strongs": [
        "H1"
      ],
      "metadata": {},
      "source": {
        "lemma": "1",
        "morph": "HNcmsc"
      }
    },
    {
      "position": 8,
      "text": "יֹשֵׁ֥ב",
      "lemma": "3427",
      "morph": "HVqrmsc",
      "strongs": [
        "H3427"
      ],
      "metadata": {},
      "source": {
        "lemma": "3427",
        "morph": "HVqrmsc"
      }
    },
    {
      "position": 9,
      "text": "אֹ֖הֶל",
      "lemma": "168",
      "morph": "HNcmsa",
      "strongs": [
        "H168"
      ],
      "metadata": {},
      "source": {
        "lemma": "168",
        "morph": "HNcmsa"
      }
    },
    {
      "position": 10,
      "text": "וּמִקְנֶֽה",
      "lemma": "c/4735",
      "morph": "HC/Ncmsa",
      "strongs": [
        "H4735"
      ],
      "metadata": {},
      "source": {
        "lemma": "c/4735",
        "morph": "HC/Ncmsa"
      }
    }
  ]
}