{
  "text": "וַיַּעֲשׂ֥וּ מִלְחָמָ֖ה עִם הַֽהַגְרִיאִ֑ים וִיט֥וּר וְנָפִ֖ישׁ וְנוֹדָֽב",
  "words": [
    {
      "position": 1,
      "text": "וַיַּעֲשׂ֥וּ",
      "lemma": "c/6213 a",
      "morph": "HC/Vqw3mp",
      "strongs": [
        "H6213"
      ],
      "metadata": {},
      "source": {
        "lemma": "c/6213 a",
        "morph": "HC/Vqw3mp"
      }
    },
    {
      "position": 2,
      "text": "מִלְחָמָ֖ה",
      "lemma": "4421",
      "morph": "HNcfsa",
      "strongs": [
        "H4421"
      ],
      "metadata": {},
      "source": {
        "lemma": "4421",
        "morph": "HNcfsa"
      }
    },
    {
      "position": 3,
      "text": "עִם",
      "lemma": "5973 a",
      "morph": "HR",
      "strongs": [
        "H5973"
      ],
      "metadata": {},
      "source": {
        "lemma": "5973 a",
        "morph": "HR"
      }
    },
    {
      "position": 4,
      "text": "הַֽהַגְרִיאִ֑ים",
      "lemma": "d/1905",
      "morph": "HTd/Ngmpa",
      "strongs": [
        "H1905"
      ],
      "metadata": {},
      "source": {
        "lemma": "d/1905",
        "morph": "HTd/Ngmpa"
      }
    },
    {
      "position": 5,
      "text": "וִיט֥וּר",
      "lemma": "c/3195",
      "morph": "HC/Np",
      "strongs": [
        "H3195"
      ],
      "metadata": {},
      "source": {
        "lemma": "c/3195",
        "morph": "HC/Np"
      }
    },
    {
      "position": 6,
      "text": "וְנָפִ֖ישׁ",
      "lemma": "c/5305",
      "morph": "HC/Np",
      "strongs": [
        "H5305"
      ],
      "metadata": {},
      "source": {
        "lemma": "c/5305",
        "morph": "HC/Np"
      }
    },
    {
      "position": 7,
      "text": "וְנוֹדָֽב",
      "lemma": "c/5114",
      "morph": "HC/Np",
      "strongs": [
        "H5114"
      ],
      "metadata": {},
      "source": {
        "lemma": "c/5114",
        "morph": "HC/Np"
      }
    }
  ]
}