{
  "text": "מַצְדִּיקֵ֥י רָשָׁ֖ע עֵ֣קֶב שֹׁ֑חַד וְצִדְקַ֥ת צַדִּיקִ֖ים יָסִ֥ירוּ מִמֶּֽנּוּ",
  "words": [
    {
      "position": 1,
      "text": "מַצְדִּיקֵ֥י",
      "lemma": "6663",
      "morph": "HVhrmpc",
      "strongs": [
        "H6663"
      ],
      "metadata": {},
      "source": {
        "lemma": "6663",
        "morph": "HVhrmpc"
      }
    },
    {
      "position": 2,
      "text": "רָשָׁ֖ע",
      "lemma": "7563",
      "morph": "HAamsa",
      "strongs": [
        "H7563"
      ],
      "metadata": {},
      "source": {
        "lemma": "7563",
        "morph": "HAamsa"
      }
    },
    {
      "position": 3,
      "text": "עֵ֣קֶב",
      "lemma": "6118",
      "morph": "HNcmsc",
      "strongs": [
        "H6118"
      ],
      "metadata": {},
      "source": {
        "lemma": "6118",
        "morph": "HNcmsc"
      }
    },
    {
      "position": 4,
      "text": "שֹׁ֑חַד",
      "lemma": "7810",
      "morph": "HNcmsa",
      "strongs": [
        "H7810"
      ],
      "metadata": {},
      "source": {
        "lemma": "7810",
        "morph": "HNcmsa"
      }
    },
    {
      "position": 5,
      "text": "וְצִדְקַ֥ת",
      "lemma": "c/6666",
      "morph": "HC/Ncfsc",
      "strongs": [
        "H6666"
      ],
      "metadata": {},
      "source": {
        "lemma": "c/6666",
        "morph": "HC/Ncfsc"
      }
    },
    {
      "position": 6,
      "text": "צַדִּיקִ֖ים",
      "lemma": "6662",
      "morph": "HAampa",
      "strongs": [
        "H6662"
      ],
      "metadata": {},
      "source": {
        "lemma": "6662",
        "morph": "HAampa"
      }
    },
    {
      "position": 7,
      "text": "יָסִ֥ירוּ",
      "lemma": "5493",
      "morph": "HVhi3mp",
      "strongs": [
        "H5493"
      ],
      "metadata": {},
      "source": {
        "lemma": "5493",
        "morph": "HVhi3mp"
      }
    },
    {
      "position": 8,
      "text": "מִמֶּֽנּוּ",
      "lemma": "4480 a",
      "morph": "HR/Sp3ms",
      "strongs": [
        "H4480"
      ],
      "metadata": {},
      "source": {
        "lemma": "4480 a",
        "morph": "HR/Sp3ms"
      }
    }
  ]
}