{
  "text": "וַיַּעַן כָּל אִישׁ רָע וּבְלִיַּעַל מֵהָאֲנָשִׁים אֲשֶׁר הָלְכוּ עִם דָּוִד וַיֹּאמְרוּ יַעַן אֲשֶׁר לֹא הָלְכוּ עִמִּי לֹא נִתֵּן לָהֶם מֵהַשָּׁלָל אֲשֶׁר הִצַּלְנוּ כִּי אִם אִישׁ אֶת אִשְׁתּוֹ וְאֶת בָּנָיו וְיִנְהֲגוּ וְיֵלֵכוּ",
  "words": [
    {
      "position": 1,
      "text": "וַיַּעַן",
      "lemma": "c/6030 b",
      "morph": "HC/Vqw3ms",
      "strongs": [
        "H6030"
      ],
      "metadata": {},
      "gematria": {
        "standard": 136,
        "ordinal": 57,
        "reduced": 19
      }
    },
    {
      "position": 2,
      "text": "כָּל",
      "lemma": "3605",
      "morph": "HNcmsc",
      "strongs": [
        "H3605"
      ],
      "metadata": {},
      "gematria": {
        "standard": 50,
        "ordinal": 23,
        "reduced": 5
      }
    },
    {
      "position": 3,
      "text": "אִישׁ",
      "lemma": "376",
      "morph": "HNcmsa",
      "strongs": [
        "H376"
      ],
      "metadata": {},
      "gematria": {
        "standard": 311,
        "ordinal": 32,
        "reduced": 5
      }
    },
    {
      "position": 4,
      "text": "רָע",
      "lemma": "7451 a",
      "morph": "HAamsa",
      "strongs": [
        "H7451"
      ],
      "metadata": {},
      "gematria": {
        "standard": 270,
        "ordinal": 36,
        "reduced": 9
      }
    },
    {
      "position": 5,
      "text": "וּבְלִיַּעַל",
      "lemma": "c/1100",
      "morph": "HC/Ncmsa",
      "strongs": [
        "H1100"
      ],
      "metadata": {},
      "gematria": {
        "standard": 148,
        "ordinal": 58,
        "reduced": 22
      }
    },
    {
      "position": 6,
      "text": "מֵהָאֲנָשִׁים",
      "lemma": "m/d/376",
      "morph": "HR/Td/Ncmpa",
      "strongs": [
        "H376"
      ],
      "metadata": {},
      "gematria": {
        "standard": 446,
        "ordinal": 88,
        "reduced": 23
      }
    },
    {
      "position": 7,
      "text": "אֲשֶׁר",
      "lemma": "834 a",
      "morph": "HTr",
      "strongs": [
        "H834"
      ],
      "metadata": {},
      "gematria": {
        "standard": 501,
        "ordinal": 42,
        "reduced": 6
      }
    },
    {
      "position": 8,
      "text": "הָלְכוּ",
      "lemma": "1980",
      "morph": "HVqp3cp",
      "strongs": [
        "H1980"
      ],
      "metadata": {},
      "gematria": {
        "standard": 61,
        "ordinal": 34,
        "reduced": 16
      }
    },
    {
      "position": 9,
      "text": "עִם",
      "lemma": "5973 a",
      "morph": "HR",
      "strongs": [
        "H5973"
      ],
      "metadata": {},
      "gematria": {
        "standard": 110,
        "ordinal": 40,
        "reduced": 11
      }
    },
    {
      "position": 10,
      "text": "דָּוִד",
      "lemma": "1732",
      "morph": "HNp",
      "strongs": [
        "H1732"
      ],
      "metadata": {},
      "gematria": {
        "standard": 14,
        "ordinal": 14,
        "reduced": 14
      }
    },
    {
      "position": 11,
      "text": "וַיֹּאמְרוּ",
      "lemma": "c/559",
      "morph": "HC/Vqw3mp",
      "strongs": [
        "H559"
      ],
      "metadata": {},
      "gematria": {
        "standard": 263,
        "ordinal": 56,
        "reduced": 20
      }
    },
    {
      "position": 12,
      "text": "יַעַן",
      "lemma": "3282",
      "morph": "HC",
      "strongs": [
        "H3282"
      ],
      "metadata": {},
      "gematria": {
        "standard": 130,
        "ordinal": 51,
        "reduced": 13
      }
    },
    {
      "position": 13,
      "text": "אֲשֶׁר",
      "lemma": "834 a",
      "morph": "HTr",
      "strongs": [
        "H834"
      ],
      "metadata": {},
      "gematria": {
        "standard": 501,
        "ordinal": 42,
        "reduced": 6
      }
    },
    {
      "position": 14,
      "text": "לֹא",
      "lemma": "3808",
      "morph": "HTn",
      "strongs": [
        "H3808"
      ],
      "metadata": {},
      "gematria": {
        "standard": 31,
        "ordinal": 13,
        "reduced": 4
      }
    },
    {
      "position": 15,
      "text": "הָלְכוּ",
      "lemma": "1980",
      "morph": "HVqp3cp",
      "strongs": [
        "H1980"
      ],
      "metadata": {},
      "gematria": {
        "standard": 61,
        "ordinal": 34,
        "reduced": 16
      }
    },
    {
      "position": 16,
      "text": "עִמִּי",
      "lemma": "5973 a",
      "morph": "HR/Sp1cs",
      "strongs": [
        "H5973"
      ],
      "metadata": {},
      "gematria": {
        "standard": 120,
        "ordinal": 39,
        "reduced": 12
      }
    },
    {
      "position": 17,
      "text": "לֹא",
      "lemma": "3808",
      "morph": "HTn",
      "strongs": [
        "H3808"
      ],
      "metadata": {},
      "gematria": {
        "standard": 31,
        "ordinal": 13,
        "reduced": 4
      }
    },
    {
      "position": 18,
      "text": "נִתֵּן",
      "lemma": "5414",
      "morph": "HVqi1cp",
      "strongs": [
        "H5414"
      ],
      "metadata": {},
      "gematria": {
        "standard": 500,
        "ordinal": 61,
        "reduced": 14
      }
    },
    {
      "position": 19,
      "text": "לָהֶם",
      "lemma": "l",
      "morph": "HR/Sp3mp",
      "metadata": {},
      "gematria": {
        "standard": 75,
        "ordinal": 41,
        "reduced": 12
      }
    },
    {
      "position": 20,
      "text": "מֵהַשָּׁלָל",
      "lemma": "m/d/7998",
      "morph": "HR/Td/Ncmsa",
      "strongs": [
        "H7998"
      ],
      "metadata": {},
      "gematria": {
        "standard": 405,
        "ordinal": 63,
        "reduced": 18
      }
    },
    {
      "position": 21,
      "text": "אֲשֶׁר",
      "lemma": "834 a",
      "morph": "HTr",
      "strongs": [
        "H834"
      ],
      "metadata": {},
      "gematria": {
        "standard": 501,
        "ordinal": 42,
        "reduced": 6
      }
    },
    {
      "position": 22,
      "text": "הִצַּלְנוּ",
      "lemma": "5337",
      "morph": "HVhp1cp",
      "strongs": [
        "H5337"
      ],
      "metadata": {},
      "gematria": {
        "standard": 181,
        "ordinal": 55,
        "reduced": 28
      }
    },
    {
      "position": 23,
      "text": "כִּי",
      "lemma": "3588 b",
      "morph": "HC",
      "strongs": [
        "H3588"
      ],
      "metadata": {},
      "gematria": {
        "standard": 30,
        "ordinal": 21,
        "reduced": 3
      }
    },
    {
      "position": 24,
      "text": "אִם",
      "lemma": "518 b",
      "morph": "HC",
      "strongs": [
        "H518"
      ],
      "metadata": {},
      "gematria": {
        "standard": 41,
        "ordinal": 25,
        "reduced": 5
      }
    },
    {
      "position": 25,
      "text": "אִישׁ",
      "lemma": "376",
      "morph": "HNcmsa",
      "strongs": [
        "H376"
      ],
      "metadata": {},
      "gematria": {
        "standard": 311,
        "ordinal": 32,
        "reduced": 5
      }
    },
    {
      "position": 26,
      "text": "אֶת",
      "lemma": "853",
      "morph": "HTo",
      "strongs": [
        "H853"
      ],
      "metadata": {},
      "gematria": {
        "standard": 401,
        "ordinal": 23,
        "reduced": 5
      }
    },
    {
      "position": 27,
      "text": "אִשְׁתּוֹ",
      "lemma": "802",
      "morph": "HNcfsc/Sp3ms",
      "strongs": [
        "H802"
      ],
      "metadata": {},
      "gematria": {
        "standard": 707,
        "ordinal": 50,
        "reduced": 14
      }
    },
    {
      "position": 28,
      "text": "וְאֶת",
      "lemma": "c/853",
      "morph": "HC/To",
      "strongs": [
        "H853"
      ],
      "metadata": {},
      "gematria": {
        "standard": 407,
        "ordinal": 29,
        "reduced": 11
      }
    },
    {
      "position": 29,
      "text": "בָּנָיו",
      "lemma": "1121 a",
      "morph": "HNcmpc/Sp3ms",
      "strongs": [
        "H1121"
      ],
      "metadata": {},
      "gematria": {
        "standard": 68,
        "ordinal": 32,
        "reduced": 14
      }
    },
    {
      "position": 30,
      "text": "וְיִנְהֲגוּ",
      "lemma": "c/5090 a",
      "morph": "HC/Vqi3mp",
      "strongs": [
        "H5090"
      ],
      "metadata": {},
      "gematria": {
        "standard": 80,
        "ordinal": 44,
        "reduced": 26
      }
    },
    {
      "position": 31,
      "text": "וְיֵלֵכוּ",
      "lemma": "c/3212",
      "morph": "HC/Vqi3mp",
      "strongs": [
        "H3212"
      ],
      "metadata": {},
      "gematria": {
        "standard": 72,
        "ordinal": 45,
        "reduced": 18
      }
    }
  ],
  "gematria": {
    "standard": 6963,
    "ordinal": 1235,
    "reduced": 384
  }
}