{
  "text": "מִתּוֹךְ וּמֵחָמָס יִגְאַל נַפְשָׁם וְיֵיקַר דָּמָם בְּעֵינָיו",
  "words": [
    {
      "position": 1,
      "text": "מִתּוֹךְ",
      "lemma": "m/8496",
      "morph": "HR/Ncmsa",
      "strongs": [
        "H8496"
      ],
      "metadata": {},
      "gematria": {
        "standard": 466,
        "ordinal": 64,
        "reduced": 16
      }
    },
    {
      "position": 2,
      "text": "וּמֵחָמָס",
      "lemma": "c/m/2555",
      "morph": "HC/R/Ncmsa",
      "strongs": [
        "H2555"
      ],
      "metadata": {},
      "gematria": {
        "standard": 154,
        "ordinal": 55,
        "reduced": 28
      }
    },
    {
      "position": 3,
      "text": "יִגְאַל",
      "lemma": "1350 a",
      "morph": "HVqi3ms",
      "strongs": [
        "H1350"
      ],
      "metadata": {},
      "gematria": {
        "standard": 44,
        "ordinal": 26,
        "reduced": 8
      }
    },
    {
      "position": 4,
      "text": "נַפְשָׁם",
      "lemma": "5315",
      "morph": "HNcbsc/Sp3mp",
      "strongs": [
        "H5315"
      ],
      "metadata": {},
      "gematria": {
        "standard": 470,
        "ordinal": 76,
        "reduced": 20
      }
    },
    {
      "position": 5,
      "text": "וְיֵיקַר",
      "lemma": "c/3365",
      "morph": "HC/Vqi3ms",
      "strongs": [
        "H3365"
      ],
      "metadata": {},
      "gematria": {
        "standard": 326,
        "ordinal": 65,
        "reduced": 11
      }
    },
    {
      "position": 6,
      "text": "דָּמָם",
      "lemma": "1818",
      "morph": "HNcmsc/Sp3mp",
      "strongs": [
        "H1818"
      ],
      "metadata": {},
      "gematria": {
        "standard": 84,
        "ordinal": 41,
        "reduced": 12
      }
    },
    {
      "position": 7,
      "text": "בְּעֵינָיו",
      "lemma": "b/5869 a",
      "morph": "HR/Ncbdc/Sp3ms",
      "strongs": [
        "H5869"
      ],
      "metadata": {},
      "gematria": {
        "standard": 148,
        "ordinal": 58,
        "reduced": 22
      }
    }
  ],
  "gematria": {
    "standard": 1692,
    "ordinal": 385,
    "reduced": 117
  }
}