{
  "text": "כֹּ֥ה אָמַ֖ר אֲדֹנָ֣י יְהוִ֑ה רָעָ֛ה אַחַ֥ת רָעָ֖ה הִנֵּ֥ה בָאָֽה",
  "words": [
    {
      "position": 1,
      "text": "כֹּ֥ה",
      "lemma": "3541",
      "morph": "HD",
      "strongs": [
        "H3541"
      ],
      "metadata": {},
      "source": {
        "lemma": "3541",
        "morph": "HD"
      }
    },
    {
      "position": 2,
      "text": "אָמַ֖ר",
      "lemma": "559",
      "morph": "HVqp3ms",
      "strongs": [
        "H559"
      ],
      "metadata": {},
      "source": {
        "lemma": "559",
        "morph": "HVqp3ms"
      }
    },
    {
      "position": 3,
      "text": "אֲדֹנָ֣י",
      "lemma": "136",
      "morph": "HNcmpc/Sp1cs",
      "strongs": [
        "H136"
      ],
      "metadata": {},
      "source": {
        "lemma": "136",
        "morph": "HNcmpc/Sp1cs"
      }
    },
    {
      "position": 4,
      "text": "יְהוִ֑ה",
      "lemma": "3069",
      "morph": "HNp",
      "strongs": [
        "H3069"
      ],
      "metadata": {},
      "source": {
        "lemma": "3069",
        "morph": "HNp"
      }
    },
    {
      "position": 5,
      "text": "רָעָ֛ה",
      "lemma": "7451 c",
      "morph": "HNcfsa",
      "strongs": [
        "H7451"
      ],
      "metadata": {},
      "source": {
        "lemma": "7451 c",
        "morph": "HNcfsa"
      }
    },
    {
      "position": 6,
      "text": "אַחַ֥ת",
      "lemma": "259",
      "morph": "HAcfsa",
      "strongs": [
        "H259"
      ],
      "metadata": {},
      "source": {
        "lemma": "259",
        "morph": "HAcfsa"
      }
    },
    {
      "position": 7,
      "text": "רָעָ֖ה",
      "lemma": "7451 c",
      "morph": "HNcfsa",
      "strongs": [
        "H7451"
      ],
      "metadata": {},
      "source": {
        "lemma": "7451 c",
        "morph": "HNcfsa"
      }
    },
    {
      "position": 8,
      "text": "הִנֵּ֥ה",
      "lemma": "2009",
      "morph": "HTm",
      "strongs": [
        "H2009"
      ],
      "metadata": {},
      "source": {
        "lemma": "2009",
        "morph": "HTm"
      }
    },
    {
      "position": 9,
      "text": "בָאָֽה",
      "lemma": "935",
      "morph": "HVqrfsa",
      "strongs": [
        "H935"
      ],
      "metadata": {},
      "source": {
        "lemma": "935",
        "morph": "HVqrfsa"
      }
    }
  ]
}