{
  "text": "וּבְנֵי מִדְיָן עֵיפָה וָעֵפֶר וַחֲנֹךְ וַאֲבִידָע וְאֶלְדָּעָה כָּל אֵלֶּה בְּנֵי קְטוּרָה",
  "words": [
    {
      "position": 1,
      "text": "וּבְנֵי",
      "lemma": "c/1121 a",
      "morph": "HC/Ncmpc",
      "strongs": [
        "H1121"
      ],
      "metadata": {},
      "gematria": {
        "standard": 68,
        "ordinal": 32,
        "reduced": 14
      }
    },
    {
      "position": 2,
      "text": "מִדְיָן",
      "lemma": "4080",
      "morph": "HNp",
      "strongs": [
        "H4080"
      ],
      "metadata": {},
      "gematria": {
        "standard": 104,
        "ordinal": 41,
        "reduced": 14
      }
    },
    {
      "position": 3,
      "text": "עֵיפָה",
      "lemma": "5891",
      "morph": "HNp",
      "strongs": [
        "H5891"
      ],
      "metadata": {},
      "gematria": {
        "standard": 165,
        "ordinal": 48,
        "reduced": 21
      }
    },
    {
      "position": 4,
      "text": "וָעֵפֶר",
      "lemma": "c/6081",
      "morph": "HC/Np",
      "strongs": [
        "H6081"
      ],
      "metadata": {},
      "gematria": {
        "standard": 356,
        "ordinal": 59,
        "reduced": 23
      }
    },
    {
      "position": 5,
      "text": "וַחֲנֹךְ",
      "lemma": "c/2585",
      "morph": "HC/Np",
      "strongs": [
        "H2585"
      ],
      "metadata": {},
      "gematria": {
        "standard": 84,
        "ordinal": 39,
        "reduced": 21
      }
    },
    {
      "position": 6,
      "text": "וַאֲבִידָע",
      "lemma": "c/28",
      "morph": "HC/Np",
      "strongs": [
        "H28"
      ],
      "metadata": {},
      "gematria": {
        "standard": 93,
        "ordinal": 39,
        "reduced": 21
      }
    },
    {
      "position": 7,
      "text": "וְאֶלְדָּעָה",
      "lemma": "c/420",
      "morph": "HC/Np",
      "strongs": [
        "H420"
      ],
      "metadata": {},
      "gematria": {
        "standard": 116,
        "ordinal": 44,
        "reduced": 26
      }
    },
    {
      "position": 8,
      "text": "כָּל",
      "lemma": "3605",
      "morph": "HNcmsc",
      "strongs": [
        "H3605"
      ],
      "metadata": {},
      "gematria": {
        "standard": 50,
        "ordinal": 23,
        "reduced": 5
      }
    },
    {
      "position": 9,
      "text": "אֵלֶּה",
      "lemma": "428",
      "morph": "HPdxcp",
      "strongs": [
        "H428"
      ],
      "metadata": {},
      "gematria": {
        "standard": 36,
        "ordinal": 18,
        "reduced": 9
      }
    },
    {
      "position": 10,
      "text": "בְּנֵי",
      "lemma": "1121 a",
      "morph": "HNcmpc",
      "strongs": [
        "H1121"
      ],
      "metadata": {},
      "gematria": {
        "standard": 62,
        "ordinal": 26,
        "reduced": 8
      }
    },
    {
      "position": 11,
      "text": "קְטוּרָה",
      "lemma": "6989",
      "morph": "HNp",
      "strongs": [
        "H6989"
      ],
      "metadata": {},
      "gematria": {
        "standard": 320,
        "ordinal": 59,
        "reduced": 23
      }
    }
  ],
  "gematria": {
    "standard": 1454,
    "ordinal": 428,
    "reduced": 185
  }
}